{
  "platform": {
    "ArduinoUno": {
      "name": "Arduino Uno",
      "components": {
        "Button": {
          "description": "Hardware Abstraction for Buttons. It provides an easy way of handling buttons.",
          "img": "arduino/switch.svg",
          "signals": {
            "isPressed": {
              "img": "arduino/button-1.svg",
              "description": "Return true if the button has been pressed"
            },
            "clicked": {
              "img": "arduino/button.svg",
              "description": "Return > 0 if the button is clicked, or 0 if not."
            }
          },
          "parameters": {
            "pin": {
              "img": "",
              "type": "uint8_t",
              "description": "buttonPin  sets the pin that this switch is connected to"
            },
            "buttonMode": {
              "img": "",
              "type": "uint8_t",
              "description": "buttonMode indicates BUTTON_PULLUP or BUTTON_PULLDOWN resistor"
            }
          },
          "variables": {},
          "methods": {},
          "singletone": false
        },

        "LED": {
          "description": "Hardware Abstraction for LEDs. It provides an easy way of handling LEDs.",
          "img": "arduino/led.svg",
          "signals": {},
          "parameters": {
            "pin": {
              "img": "",
              "type": "uint8_t",
              "description": "ledPin the pin connected to this LED"
            },
            "buttonMode": {
              "img": "",
              "type": "uint8_t",
              "description": "buttonMode indicates BUTTON_PULLUP or BUTTON_PULLDOWN resistor"
            }
          },
          "variables": {},
          "methods": {
            "on": {
              "img": "arduino/switch-on.svg",
              "parameters": {},
              "description": "Set this LED on"
            },
            "off": {
              "img": "arduino/switch-off.svg",
              "parameters": {},
              "description": "Set this LED off"
            }
          },
          "singletone": false
        }
      }
    }
  }
}
